protoc_gen_openapiv2/__init__.py
protoc_gen_openapiv2/options/__init__.py
protoc_gen_openapiv2/options/annotations_pb2.py
protoc_gen_openapiv2/options/annotations_pb2.pyi
protoc_gen_openapiv2/options/openapiv2_pb2.py
protoc_gen_openapiv2/options/openapiv2_pb2.pyi
tecton/__init__.py
tecton/_gen_version.py
tecton/_stamp.py
tecton/aggregation_functions.py
tecton/fco_listers.py
tecton/py.typed
tecton/pytest_tecton.py
tecton/repo_utils.py
tecton/run_api_consts.py
tecton/snowflake_context.py
tecton/tecton_context.py
tecton/tecton_test_repo.py
tecton/types.py
tecton/version.py
tecton/_internals/__init__.py
tecton/_internals/analytics.py
tecton/_internals/athena_api.py
tecton/_internals/delete_keys_api.py
tecton/_internals/display.py
tecton/_internals/env_utils.py
tecton/_internals/errors.py
tecton/_internals/find_spark.py
tecton/_internals/infra_operations.py
tecton/_internals/ingest_utils.py
tecton/_internals/ingestion.py
tecton/_internals/materialization_api.py
tecton/_internals/metadata_service.py
tecton/_internals/mock_source_utils.py
tecton/_internals/model_artifact_provider.py
tecton/_internals/model_utils.py
tecton/_internals/offline_store_credentials.py
tecton/_internals/query_helper.py
tecton/_internals/querytree_api.py
tecton/_internals/run_api.py
tecton/_internals/sdk_decorators.py
tecton/_internals/secret_resolver.py
tecton/_internals/spark_api.py
tecton/_internals/spark_utils.py
tecton/_internals/tecton_pydantic.py
tecton/_internals/tecton_typeguard.py
tecton/_internals/type_utils.py
tecton/_internals/utils.py
tecton/_internals/validations_api.py
tecton/_internals/metadata_service_impl/__init__.py
tecton/_internals/metadata_service_impl/auth_lib.py
tecton/_internals/metadata_service_impl/request_lib.py
tecton/_internals/metadata_service_impl/service_modules.py
tecton/_internals/metadata_service_impl/tests/__init__.py
tecton/_internals/metadata_service_impl/tests/test_http_client.py
tecton/_internals/metadata_service_impl/tests/test_request_lib.py
tecton-1.2.13.dist-info/METADATA
tecton-1.2.13.dist-info/WHEEL
tecton-1.2.13.dist-info/entry_points.txt
tecton-1.2.13.dist-info/top_level.txt
tecton-1.2.13.dist-info/RECORD
