Metadata-Version: 2.1
Name: tecton
Version: 1.2.13
Summary: Tecton Python SDK
Author-email: "Tecton, Inc." <support@tecton.ai>
License: Tecton Proprietary
Project-URL: Homepage, https://tecton.ai
Project-URL: Documentation, https://docs.tecton.ai
Classifier: Programming Language :: Python :: 3
Classifier: Operating System :: OS Independent
Classifier: License :: Other/Proprietary License
Requires-Python: >=3.7
Requires-Dist: attrs >=21.3.0
Requires-Dist: boto3
Requires-Dist: cryptography >=45.0
Requires-Dist: jinja2 ~=3.0
Requires-Dist: numpy ~=1.16
Requires-Dist: pathspec
Requires-Dist: protobuf <5,>=4.21.12
Requires-Dist: pypika ~=0.48.9
Requires-Dist: pytimeparse
Requires-Dist: pandas >=1.0
Requires-Dist: texttable
Requires-Dist: requests
Requires-Dist: colorama ~=0.4
Requires-Dist: tqdm ~=4.41
Requires-Dist: yaspin <3,>=0.16
Requires-Dist: typing-extensions ~=4.1
Requires-Dist: pygments >=2.7.4
Requires-Dist: pytest
Requires-Dist: click ~=8.0
Requires-Dist: typeguard ~=2.0
Requires-Dist: sqlparse
Requires-Dist: semantic-version
Requires-Dist: pyarrow >=8
Requires-Dist: pydantic <3,>=1.10.13
Requires-Dist: pyyaml
Requires-Dist: setuptools
Requires-Dist: pip
Requires-Dist: pex ~=2.1
Requires-Dist: rich
Requires-Dist: rich-click >=1.0
Requires-Dist: pendulum ~=2.1 ; python_version < "3.10"
Requires-Dist: deltalake >=0.18.2 ; python_version > "3.7"
Requires-Dist: uv <1.0,>=0.4.1 ; python_version > "3.7"
Requires-Dist: pendulum ~=3.0.0 ; python_version >= "3.10"
Provides-Extra: athena
Requires-Dist: awswrangler ~=3.0 ; extra == 'athena'
Provides-Extra: databricks-connect
Requires-Dist: databricks-connect[sql] ~=10.4.12 ; extra == 'databricks-connect'
Provides-Extra: databricks-connect10
Requires-Dist: databricks-connect[sql] ~=10.4.12 ; extra == 'databricks-connect10'
Provides-Extra: databricks-connect11
Requires-Dist: databricks-connect[sql] ~=11.3.12 ; extra == 'databricks-connect11'
Provides-Extra: databricks-connect9
Requires-Dist: databricks-connect[sql] ~=9.1.23 ; extra == 'databricks-connect9'
Provides-Extra: materialization
Requires-Dist: statsd ==3.3.0 ; extra == 'materialization'
Requires-Dist: urllib3 <2.0.0 ; extra == 'materialization'
Requires-Dist: mmh3 ==3.1.0 ; (python_version < "3.8") and extra == 'materialization'
Requires-Dist: mmh3 <6.0,>=3.1.0 ; (python_version >= "3.8") and extra == 'materialization'
Provides-Extra: ml-extras
Requires-Dist: torch >=2.0.0 ; extra == 'ml-extras'
Requires-Dist: transformers >=4.40.0 ; extra == 'ml-extras'
Provides-Extra: pyspark
Requires-Dist: pyspark[sql] ~=3.2 ; extra == 'pyspark'
Provides-Extra: pyspark3
Requires-Dist: pyspark[sql] ~=3.2 ; extra == 'pyspark3'
Provides-Extra: pyspark3.1
Requires-Dist: pyspark[sql] ~=3.1.2 ; extra == 'pyspark3.1'
Provides-Extra: pyspark3.2
Requires-Dist: pyspark[sql] ~=3.2.1 ; extra == 'pyspark3.2'
Provides-Extra: pyspark3.3
Requires-Dist: pyspark[sql] ~=3.3.2 ; extra == 'pyspark3.3'
Provides-Extra: rift
Requires-Dist: duckdb ==1.1.2 ; extra == 'rift'
Requires-Dist: pyarrow >=11.0.0 ; extra == 'rift'
Requires-Dist: pandas >=1.5 ; extra == 'rift'
Requires-Dist: ray ~=2.10 ; extra == 'rift'
Requires-Dist: pyiceberg[glue] <0.10,>=0.7 ; extra == 'rift'
Requires-Dist: snowflake-connector-python[pandas] ~=3.10 ; extra == 'rift'
Requires-Dist: snowflake-snowpark-python[pandas] ~=1.0 ; extra == 'rift'
Requires-Dist: tecton-rift-extensions ==1.2.0 ; extra == 'rift'
Provides-Extra: rift-materialization
Requires-Dist: duckdb ==1.1.2 ; extra == 'rift-materialization'
Requires-Dist: pyarrow ~=15.0.0 ; extra == 'rift-materialization'
Requires-Dist: pandas >=1.5 ; extra == 'rift-materialization'
Requires-Dist: pyiceberg[glue] <0.10,>=0.7 ; extra == 'rift-materialization'
Requires-Dist: snowflake-connector-python[pandas] ~=3.10 ; extra == 'rift-materialization'
Requires-Dist: snowflake-snowpark-python[pandas] ~=1.0 ; extra == 'rift-materialization'
Requires-Dist: google-cloud-bigquery[pandas] ~=3.16 ; extra == 'rift-materialization'
Requires-Dist: google-cloud-bigquery-storage ~=2.25 ; extra == 'rift-materialization'
Requires-Dist: google-cloud-storage ~=2.8 ; extra == 'rift-materialization'
Requires-Dist: redshift-connector ~=2.1 ; extra == 'rift-materialization'
Requires-Dist: boto3 >=1.12.6 ; extra == 'rift-materialization'
Requires-Dist: deltalake <1.0 ; extra == 'rift-materialization'
Requires-Dist: psycopg[binary] ~=3.2 ; extra == 'rift-materialization'
Requires-Dist: tecton-rift-extensions ==1.2.0 ; extra == 'rift-materialization'
Provides-Extra: snowflake
Requires-Dist: snowflake-connector-python[pandas] ~=3.10 ; extra == 'snowflake'
Requires-Dist: snowflake-snowpark-python[pandas] ~=1.0 ; extra == 'snowflake'
